showprogress/__init__.py
showprogress/memory.py
showprogress/progress.py
showprogress-0.0.24.dist-info/DESCRIPTION.rst
showprogress-0.0.24.dist-info/METADATA
showprogress-0.0.24.dist-info/RECORD
showprogress-0.0.24.dist-info/WHEEL
showprogress-0.0.24.dist-info/metadata.json
showprogress-0.0.24.dist-info/top_level.txt
